shantay/__init__.py
shantay/__main__.py
shantay/_category.py
shantay/_keyword.py
shantay/_platform.py
shantay/builtin.parquet
shantay/color.py
shantay/digest.py
shantay/dsa_sor.py
shantay/framing.py
shantay/log.py
shantay/logutil.py
shantay/metadata.py
shantay/model.py
shantay/multiprocessor.py
shantay/pool.py
shantay/processor.py
shantay/progress.py
shantay/py.typed
shantay/schema.py
shantay/stats.py
shantay/task.py
shantay/tool.py
shantay/util.py
shantay/viz.py
shantay-0.6.0.dist-info/entry_points.txt
shantay-0.6.0.dist-info/licenses/LICENSE
shantay-0.6.0.dist-info/WHEEL
shantay-0.6.0.dist-info/METADATA
shantay-0.6.0.dist-info/RECORD
