Metadata-Version: 2.4
Name: shantay
Version: 0.6.0
Summary: investigating the EU's DSA transparency database
Keywords: batch processing,EU DSA,statement of reason
Author-email: Robert Grimm <rgrimm@alum.mit.edu>
Requires-Python: >=3.12
Classifier: Intended Audience :: Information Technology
Classifier: Intended Audience :: Science/Research
Classifier: License :: OSI Approved :: Apache Software License
Classifier: Programming Language :: Python :: 3
Classifier: Topic :: Database
Classifier: Topic :: Scientific/Engineering :: Information Analysis
Classifier: Topic :: Sociology
Classifier: Topic :: System :: Archiving
Classifier: Topic :: Terminals
License-File: LICENSE
Requires-Dist: altair
Requires-Dist: vl-convert-python
Requires-Dist: polars >= 1.33.1
Requires-Dist: pyarrow
Requires-Dist: great_tables
Requires-Dist: ipython
Requires-Dist: ipykernel
Requires-Dist: mistune
Project-URL: repository, https://github.com/apparebit/shantay
